LICENSE
MANIFEST.in
README.rst
requirements.txt
setup.py
helga_elo/__init__.py
helga_elo/plugin.py
helga_elo.egg-info/PKG-INFO
helga_elo.egg-info/SOURCES.txt
helga_elo.egg-info/dependency_links.txt
helga_elo.egg-info/entry_points.txt
helga_elo.egg-info/requires.txt
helga_elo.egg-info/top_level.txt
helga_elo.egg-info/zip-safe
venv/lib/python2.7/no-global-site-packages.txt
venv/lib/python2.7/orig-prefix.txt
venv/lib/python2.7/site-packages/Twisted-16.4.1.dist-info/entry_points.txt
venv/lib/python2.7/site-packages/Twisted-16.4.1.dist-info/top_level.txt
venv/lib/python2.7/site-packages/cffi-1.8.3.dist-info/entry_points.txt
venv/lib/python2.7/site-packages/cffi-1.8.3.dist-info/top_level.txt
venv/lib/python2.7/site-packages/cryptography-1.5.dist-info/entry_points.txt
venv/lib/python2.7/site-packages/cryptography-1.5.dist-info/top_level.txt
venv/lib/python2.7/site-packages/decorator-3.4.0.dist-info/top_level.txt
venv/lib/python2.7/site-packages/distribute-0.7.3-py2.7.egg-info/SOURCES.txt
venv/lib/python2.7/site-packages/distribute-0.7.3-py2.7.egg-info/dependency_links.txt
venv/lib/python2.7/site-packages/distribute-0.7.3-py2.7.egg-info/installed-files.txt
venv/lib/python2.7/site-packages/distribute-0.7.3-py2.7.egg-info/requires.txt
venv/lib/python2.7/site-packages/distribute-0.7.3-py2.7.egg-info/top_level.txt
venv/lib/python2.7/site-packages/elo-0.1.dist-info/top_level.txt
venv/lib/python2.7/site-packages/enum34-1.1.6.dist-info/top_level.txt
venv/lib/python2.7/site-packages/funcsigs-1.0.2.dist-info/top_level.txt
venv/lib/python2.7/site-packages/helga-1.7.5.dist-info/entry_points.txt
venv/lib/python2.7/site-packages/helga-1.7.5.dist-info/top_level.txt
venv/lib/python2.7/site-packages/idna-2.1.dist-info/top_level.txt
venv/lib/python2.7/site-packages/ipaddress-1.0.17.dist-info/top_level.txt
venv/lib/python2.7/site-packages/mock-2.0.0.dist-info/top_level.txt
venv/lib/python2.7/site-packages/mongomock-3.6.0.dist-info/top_level.txt
venv/lib/python2.7/site-packages/pbr-1.10.0.dist-info/entry_points.txt
venv/lib/python2.7/site-packages/pbr-1.10.0.dist-info/top_level.txt
venv/lib/python2.7/site-packages/pbr/tests/testpackage/CHANGES.txt
venv/lib/python2.7/site-packages/pbr/tests/testpackage/LICENSE.txt
venv/lib/python2.7/site-packages/pbr/tests/testpackage/README.txt
venv/lib/python2.7/site-packages/pbr/tests/testpackage/extra-file.txt
venv/lib/python2.7/site-packages/pbr/tests/testpackage/git-extra-file.txt
venv/lib/python2.7/site-packages/pbr/tests/testpackage/test-requirements.txt
venv/lib/python2.7/site-packages/pbr/tests/testpackage/data_files/a.txt
venv/lib/python2.7/site-packages/pbr/tests/testpackage/data_files/b.txt
venv/lib/python2.7/site-packages/pbr/tests/testpackage/pbr_testpackage/package_data/1.txt
venv/lib/python2.7/site-packages/pbr/tests/testpackage/pbr_testpackage/package_data/2.txt
venv/lib/python2.7/site-packages/pip-8.1.2.dist-info/entry_points.txt
venv/lib/python2.7/site-packages/pip-8.1.2.dist-info/top_level.txt
venv/lib/python2.7/site-packages/pyOpenSSL-16.1.0.dist-info/top_level.txt
venv/lib/python2.7/site-packages/pyasn1-0.1.9.dist-info/top_level.txt
venv/lib/python2.7/site-packages/pycparser-2.14.dist-info/top_level.txt
venv/lib/python2.7/site-packages/pymongo-3.3.0.dist-info/top_level.txt
venv/lib/python2.7/site-packages/pystache-0.5.4.dist-info/entry_points.txt
venv/lib/python2.7/site-packages/pystache-0.5.4.dist-info/top_level.txt
venv/lib/python2.7/site-packages/pystache/tests/data/locator/template.txt
venv/lib/python2.7/site-packages/pystache/tests/examples/inner_partial.txt
venv/lib/python2.7/site-packages/pystache/tests/examples/template_partial.txt
venv/lib/python2.7/site-packages/sentinels-1.0.0.dist-info/namespace_packages.txt
venv/lib/python2.7/site-packages/sentinels-1.0.0.dist-info/top_level.txt
venv/lib/python2.7/site-packages/setuptools-27.2.0.dist-info/dependency_links.txt
venv/lib/python2.7/site-packages/setuptools-27.2.0.dist-info/entry_points.txt
venv/lib/python2.7/site-packages/setuptools-27.2.0.dist-info/top_level.txt
venv/lib/python2.7/site-packages/six-1.10.0.dist-info/top_level.txt
venv/lib/python2.7/site-packages/smokesignal-0.5.dist-info/top_level.txt
venv/lib/python2.7/site-packages/twisted/internet/iocpreactor/notes.txt
venv/lib/python2.7/site-packages/wheel/eggnames.txt
venv/lib/python2.7/site-packages/wheel-0.30.0a0.dist-info/LICENSE.txt
venv/lib/python2.7/site-packages/wheel-0.30.0a0.dist-info/entry_points.txt
venv/lib/python2.7/site-packages/wheel-0.30.0a0.dist-info/top_level.txt
venv/lib/python2.7/site-packages/zope.interface-4.3.2.dist-info/namespace_packages.txt
venv/lib/python2.7/site-packages/zope.interface-4.3.2.dist-info/top_level.txt
venv/lib64/python2.7/no-global-site-packages.txt
venv/lib64/python2.7/orig-prefix.txt
venv/lib64/python2.7/site-packages/Twisted-16.4.1.dist-info/entry_points.txt
venv/lib64/python2.7/site-packages/Twisted-16.4.1.dist-info/top_level.txt
venv/lib64/python2.7/site-packages/cffi-1.8.3.dist-info/entry_points.txt
venv/lib64/python2.7/site-packages/cffi-1.8.3.dist-info/top_level.txt
venv/lib64/python2.7/site-packages/cryptography-1.5.dist-info/entry_points.txt
venv/lib64/python2.7/site-packages/cryptography-1.5.dist-info/top_level.txt
venv/lib64/python2.7/site-packages/decorator-3.4.0.dist-info/top_level.txt
venv/lib64/python2.7/site-packages/distribute-0.7.3-py2.7.egg-info/SOURCES.txt
venv/lib64/python2.7/site-packages/distribute-0.7.3-py2.7.egg-info/dependency_links.txt
venv/lib64/python2.7/site-packages/distribute-0.7.3-py2.7.egg-info/installed-files.txt
venv/lib64/python2.7/site-packages/distribute-0.7.3-py2.7.egg-info/requires.txt
venv/lib64/python2.7/site-packages/distribute-0.7.3-py2.7.egg-info/top_level.txt
venv/lib64/python2.7/site-packages/elo-0.1.dist-info/top_level.txt
venv/lib64/python2.7/site-packages/enum34-1.1.6.dist-info/top_level.txt
venv/lib64/python2.7/site-packages/funcsigs-1.0.2.dist-info/top_level.txt
venv/lib64/python2.7/site-packages/helga-1.7.5.dist-info/entry_points.txt
